metafunctions/__init__.py
metafunctions/api.py
metafunctions/exceptions.py
metafunctions/map.py
metafunctions/operators.py
metafunctions/util.py
metafunctions/core/__init__.py
metafunctions/core/base.py
metafunctions/core/call_state.py
metafunctions/core/concurrent.py
metafunctions/core/decorators.py
metafunctions/tests/__init__.py
metafunctions/tests/simple_nodes.py
metafunctions/tests/test_api.py
metafunctions/tests/test_at_operator.py
metafunctions/tests/test_call_state.py
metafunctions/tests/test_concurrent.py
metafunctions/tests/test_deferred_value.py
metafunctions/tests/test_function_chain.py
metafunctions/tests/test_function_merge.py
metafunctions/tests/test_imports.py
metafunctions/tests/test_map.py
metafunctions/tests/test_pipe.py
metafunctions/tests/test_simple_function.py
metafunctions/tests/test_star.py
metafunctions/tests/test_util.py
metafunctions/tests/util.py
metafunctions-1.1.1.dist-info/LICENSE
metafunctions-1.1.1.dist-info/METADATA
metafunctions-1.1.1.dist-info/WHEEL
metafunctions-1.1.1.dist-info/top_level.txt
metafunctions-1.1.1.dist-info/RECORD
