Metadata-Version: 2.1
Name: metafunctions
Version: 1.1.1
Summary: Metafunctions is a function composition and data pipelining library
Home-page: https://github.com/ForeverWintr/metafunctions
Author: Tom Rutherford
Author-email: foreverwintr@gmail.com
License: MIT
Keywords: functional-programming function-composition
Platform: UNKNOWN
Classifier: Development Status :: 5 - Production/Stable
Classifier: Intended Audience :: Developers
Classifier: Topic :: Software Development :: Libraries :: Python Modules
Classifier: License :: OSI Approved :: MIT License
Classifier: Programming Language :: Python :: 3.5
Classifier: Programming Language :: Python :: 3.6
Classifier: Programming Language :: Python :: 3.7
Classifier: Programming Language :: Python :: 3.8
Classifier: Programming Language :: Python :: 3.9
Classifier: Programming Language :: Python :: 3.10
Classifier: Programming Language :: Python :: 3.11
License-File: LICENSE
Requires-Dist: ansicolors (>=1.1.8)
